dendrite_sdk/__init__.py
dendrite_sdk/_cli/main.py
dendrite_sdk/_common/_exceptions/__init__.py
dendrite_sdk/_common/_exceptions/_constants.py
dendrite_sdk/_common/_exceptions/dendrite_exception.py
dendrite_sdk/async_api/__init__.py
dendrite_sdk/async_api/_api/__init__.py
dendrite_sdk/async_api/_api/_http_client.py
dendrite_sdk/async_api/_api/browser_api_client.py
dendrite_sdk/async_api/_api/dto/__init__.py
dendrite_sdk/async_api/_api/dto/ask_page_dto.py
dendrite_sdk/async_api/_api/dto/authenticate_dto.py
dendrite_sdk/async_api/_api/dto/extract_dto.py
dendrite_sdk/async_api/_api/dto/get_elements_dto.py
dendrite_sdk/async_api/_api/dto/get_interaction_dto.py
dendrite_sdk/async_api/_api/dto/get_session_dto.py
dendrite_sdk/async_api/_api/dto/google_search_dto.py
dendrite_sdk/async_api/_api/dto/make_interaction_dto.py
dendrite_sdk/async_api/_api/dto/try_run_script_dto.py
dendrite_sdk/async_api/_api/dto/upload_auth_session_dto.py
dendrite_sdk/async_api/_api/response/__init__.py
dendrite_sdk/async_api/_api/response/ask_page_response.py
dendrite_sdk/async_api/_api/response/extract_response.py
dendrite_sdk/async_api/_api/response/get_element_response.py
dendrite_sdk/async_api/_api/response/google_search_response.py
dendrite_sdk/async_api/_api/response/interaction_response.py
dendrite_sdk/async_api/_api/response/session_response.py
dendrite_sdk/async_api/_common/__init__.py
dendrite_sdk/async_api/_common/constants.py
dendrite_sdk/async_api/_common/event_sync.py
dendrite_sdk/async_api/_common/status.py
dendrite_sdk/async_api/_core/__init__.py
dendrite_sdk/async_api/_core/_impl_browser.py
dendrite_sdk/async_api/_core/_impl_mapping.py
dendrite_sdk/async_api/_core/_js/__init__.py
dendrite_sdk/async_api/_core/_js/eventListenerPatch.js
dendrite_sdk/async_api/_core/_js/generateDendriteIDs.js
dendrite_sdk/async_api/_core/_js/generateDendriteIDsIframe.js
dendrite_sdk/async_api/_core/_managers/__init__.py
dendrite_sdk/async_api/_core/_managers/page_manager.py
dendrite_sdk-0.2.2.dist-info/LICENSE
dendrite_sdk-0.2.2.dist-info/METADATA
dendrite_sdk-0.2.2.dist-info/WHEEL
dendrite_sdk-0.2.2.dist-info/entry_points.txt
dendrite_sdk-0.2.2.dist-info/RECORD
