Metadata-Version: 2.1
Name: dendrite-sdk
Version: 0.2.2
Summary: Dendrite is a suite of tools that makes it easy to create web integrations for AI agents. With Dendrite your can: Authenticate on websites, Interact with elements, Extract structured data, Download and upload files, Fill out forms
Home-page: https://dendrite.systems
Keywords: AI agent,playwright,web,web agents,automation,web extraction,browser
Author: Arian Hanifi
Author-email: arian@dendrite.se
Requires-Python: >=3.9,<4.0
Classifier: Development Status :: 3 - Alpha
Classifier: License :: OSI Approved :: MIT License
Classifier: Operating System :: OS Independent
Classifier: Programming Language :: Python :: 3
Classifier: Programming Language :: Python :: 3.9
Classifier: Programming Language :: Python :: 3.10
Classifier: Programming Language :: Python :: 3.11
Classifier: Programming Language :: Python :: 3.12
Classifier: Programming Language :: Python :: 3.13
Requires-Dist: bs4 (>=0.0.2,<0.0.3)
Requires-Dist: httpx (>=0.27.2,<0.28.0)
Requires-Dist: loguru (>=0.7.2,<0.8.0)
Requires-Dist: lxml (>=5.2.1,<6.0.0)
Requires-Dist: markdownify (>=0.13.1,<0.14.0)
Requires-Dist: playwright (>=1.43.0,<2.0.0)
Requires-Dist: pydantic (>=2.6.0,<3.0.0)
Requires-Dist: typing-extensions (>=4.12.0,<5.0.0)
Project-URL: Documentation, https://docs.dendrite.systems/introduction
Project-URL: Repository, https://github.com/dendrite-systems/dendrite-python-sdk
